itensorpy/__init__.py
itensorpy/christoffel.py
itensorpy/curvature.py
itensorpy/einstein.py
itensorpy/metric.py
itensorpy/ricci.py
itensorpy/riemann.py
itensorpy/spacetimes.py
itensorpy/utils.py
itensorpy/differential_ops/__init__.py
itensorpy/differential_ops/core.py
itensorpy/differential_ops/curl.py
itensorpy/differential_ops/divergency.py
itensorpy/differential_ops/gradient.py
itensorpy/differential_ops/jacobian_hessian.py
itensorpy/differential_ops/laplacian.py
itensorpy/matrix_ops/__init__.py
itensorpy/matrix_ops/core.py
itensorpy/matrix_ops/determinant.py
itensorpy/matrix_ops/eigen.py
itensorpy/matrix_ops/linear_solve.py
itensorpy/matrix_ops/multiplication.py
itensorpy/tensor_ops/__init__.py
itensorpy/tensor_ops/arithmetic.py
itensorpy/tensor_ops/contraction.py
itensorpy/tensor_ops/core.py
itensorpy/tensor_ops/einsum.py
itensorpy/tensor_ops/shape.py
itensorpy-0.3.1.dist-info/licenses/LICENSE
itensorpy-0.3.1.dist-info/METADATA
itensorpy-0.3.1.dist-info/WHEEL
itensorpy-0.3.1.dist-info/top_level.txt
itensorpy-0.3.1.dist-info/RECORD
